{
  "v": "5.10.0",
  "fr": 30,
  "ip": 0,
  "op": 180,
  "w": 512,
  "h": 512,
  "nm": "lcoe-fab-sunburst-v1-compat",
  "ddd": 0,
  "assets": [],
  "layers": [
    { "ddd": 0, "ind": 1, "ty": 4, "nm": "Logo", "sr": 1,
      "ks": { "o": {"a":0,"k":100}, "r": {"a":0,"k":0}, "p": {"a":0,"k":[256,256,0]}, "a": {"a":0,"k":[0,0,0]}, "s": {"a":0,"k":[100,100,100]} },
      "shapes": [ { "ty": "gr", "nm": "Logo Group Placeholder", "it": [] } ],
      "ip": 0, "op": 180, "st": 0, "bm": 0
    },
    { "ddd": 0, "ind": 2, "ty": 4, "nm": "RaysOuter", "sr": 1,
      "ks": {
        "o": {"a":1,"k":[ {"t":0,"s":[0],"e":[45]}, {"t":27,"s":[45],"e":[45]}, {"t":108,"s":[45],"e":[20]}, {"t":153,"s":[20],"e":[0]}, {"t":180,"s":[0]} ]},
        "r": {"a":1,"k":[ {"t":0,"s":[0],"e":[90]}, {"t":180,"s":[90]} ]},
        "p": {"a":0,"k":[256,256,0]},
        "a": {"a":0,"k":[0,0,0]},
        "s": {"a":1,"k":[ {"t":0,"s":[100,100,100],"e":[112,112,100]}, {"t":27,"s":[112,112,100],"e":[130,130,100]}, {"t":108,"s":[130,130,100],"e":[112,112,100]}, {"t":153,"s":[112,112,100],"e":[100,100,100]}, {"t":180,"s":[100,100,100]} ]}
      },
      "shapes": [
        { "ty": "gr", "nm": "Outer Wedge", "it": [
          { "ty": "sh", "ks": { "a": 0, "k": { "i": [[0,0],[0,0],[0,0],[0,0]], "o": [[0,0],[0,0],[0,0],[0,0]], "v": [[218.795,-22.996],[218.795,22.996],[95.473,10.044],[95.473,-10.044]], "c": true } }, "nm": "Wedge Path" },
          { "ty": "fl", "c": {"a":0,"k":[0.992,0.721,0.074,1]}, "o": {"a":0,"k":100}, "r": 1, "nm": "Solid Fill" },
          { "ty": "tr", "p": {"a":0,"k":[0,0]}, "a": {"a":0,"k":[0,0]}, "s": {"a":0,"k":[100,100]}, "r": {"a":0,"k":0}, "o": {"a":0,"k":100}, "sk": {"a":0,"k":0}, "sa": {"a":0,"k":0}, "nm":"Transform" }
        ]},
        { "ty": "rp", "nm": "Repeater", "c": {"a":0,"k":18}, "o": {"a":0,"k":0}, "m":1, "ix":1, "tr": {"ty":"tr","p":{"a":0,"k":[0,0]},"a":{"a":0,"k":[0,0]},"s":{"a":0,"k":[100,100]},"r":{"a":0,"k":20},"o":{"a":0,"k":0},"so":{"a":0,"k":100},"eo":{"a":0,"k":100}} }
      ],
      "ip": 0, "op": 180, "st": 0, "bm": 0
    },
    { "ddd": 0, "ind": 3, "ty": 4, "nm": "RaysInner", "sr": 1,
      "ks": {
        "o": {"a":1,"k":[ {"t":0,"s":[0],"e":[35]}, {"t":27,"s":[35],"e":[35]}, {"t":108,"s":[35],"e":[18]}, {"t":153,"s":[18],"e":[0]}, {"t":180,"s":[0]} ]},
        "r": {"a":1,"k":[ {"t":0,"s":[0],"e":[-90]}, {"t":180,"s":[-90]} ]},
        "p": {"a":0,"k":[256,256,0]}, "a": {"a":0,"k":[0,0,0]},
        "s": {"a":1,"k":[ {"t":0,"s":[95,95,100],"e":[105,105,100]}, {"t":27,"s":[105,105,100],"e":[118,118,100]}, {"t":108,"s":[118,118,100],"e":[104,104,100]}, {"t":153,"s":[104,104,100],"e":[95,95,100]}, {"t":180,"s":[95,95,100]} ]}
      },
      "shapes": [
        { "ty": "gr", "nm": "Inner Wedge", "it": [
          { "ty": "sh", "ks": { "a": 0, "k": { "i": [[0,0],[0,0],[0,0],[0,0]], "o": [[0,0],[0,0],[0,0],[0,0]], "v": [[219.464,-15.346],[219.464,15.346],[95.767,6.696],[95.767,-6.696]], "c": true } }, "nm": "Wedge Path" },
          { "ty": "fl", "c": {"a":0,"k":[1,0.435,0,1]}, "o": {"a":0,"k":100}, "r": 1, "nm": "Solid Fill 2" },
          { "ty": "tr", "p": {"a":0,"k":[0,0]}, "a": {"a":0,"k":[0,0]}, "s": {"a":0,"k":[100,100]}, "r": {"a":0,"k":0}, "o": {"a":0,"k":100}, "sk": {"a":0,"k":0}, "sa": {"a":0,"k":0}, "nm":"Transform" }
        ]},
        { "ty": "rp", "nm": "Repeater", "c": {"a":0,"k":18}, "o": {"a":0,"k":0}, "m":1, "ix":1, "tr": {"ty":"tr","p":{"a":0,"k":[0,0]},"a":{"a":0,"k":[0,0]},"s":{"a":0,"k":[100,100]},"r":{"a":0,"k":20},"o":{"a":0,"k":0},"so":{"a":0,"k":100},"eo":{"a":0,"k":100}} }
      ],
      "ip": 0, "op": 180, "st": 0, "bm": 0
    }
  ],
  "markers": []
}
